{
  "dungeons": [
    {
      "id": 1,
      "name": "天然要害薩斯塔夏溶洞",
      "level": 15,
      "type": "四人迷宮",
      "expansion": "2.x",
      "image": null,
      "tombstoneReward": "詩學古典神典石: 20",
      "specialDrops": ["九宮幻卡：魚人", "管弦樂琴樂譜：昏暗的深處", "溶洞鹹淡水"],
      "mechanics": "注意BOSS的範圍攻擊，小怪會召喚援軍。",
      "description": "位於拉諾西亞的海盜洞窟，充滿了寶藏和危險。"
    },
    {
      "id": 2,
      "name": "地下靈殿塔姆·塔拉墓園",
      "level": 16,
      "type": "四人迷宮",
      "expansion": "2.x",
      "image": null,
      "tombstoneReward": "詩學古典神典石: 20",
      "specialDrops": ["陳舊的樂譜：漆黑的誓言"],
      "mechanics": "避開陷阱機關，注意亡靈怪物的詛咒效果。",
      "description": "古老的墓園迷宮，充滿了不死生物和黑暗魔法。"
    },
    {
      "id": 3,
      "name": "封鎖坑道銅鈴銅山",
      "level": 17,
      "type": "四人迷宮",
      "expansion": "2.x",
      "image": null,
      "tombstoneReward": "詩學古典神典石: 20",
      "specialDrops": ["管弦樂琴樂譜：地下坑道"],
      "mechanics": "利用炸彈清除路障，小心礦車軌道。",
      "description": "廢棄的銅礦場，隱藏著豐富的礦物和危險的陷阱。"
    },
    {
      "id": 4,
      "name": "魔獸領域日影地修練所",
      "level": 20,
      "type": "四人迷宮",
      "expansion": "2.x",
      "image": null,
      "tombstoneReward": "詩學古典神典石: 25",
      "specialDrops": ["管弦樂琴樂譜：修行"],
      "mechanics": "在競技場內與各種魔獸戰鬥，注意不同敵人的攻擊模式。",
      "description": "訓練格鬥士的秘密場所，各種危險的魔獸在此等待挑戰者。"
    },
    {
      "id": 5,
      "name": "監獄廢墟托托·拉克千獄",
      "level": 24,
      "type": "四人迷宮",
      "expansion": "2.x",
      "image": null,
      "tombstoneReward": "詩學古典神典石: 30",
      "specialDrops": ["管弦樂琴樂譜：千聲悲鳴", "千獄幼苗"],
      "mechanics": "利用光源照明，小心暗處的怪物突襲。",
      "description": "古老的監獄遺跡，陰暗的環境中潛藏著無數危險。"
    },
    {
      "id": 6,
      "name": "名門府邸靜語莊園",
      "level": 28,
      "type": "四人迷宮",
      "expansion": "2.x",
      "image": null,
      "tombstoneReward": "詩學古典神典石: 35",
      "specialDrops": ["九宮幻卡：夢魔", "管弦樂琴樂譜：少女的哀歌", "莊園蠟"],
      "mechanics": "穿越迷宮般的房間，注意隱藏的機關和陷阱。",
      "description": "貴族的豪華莊園，如今被詛咒的生物所佔據。"
    },
    {
      "id": 7,
      "name": "休養勝地布雷福洛克斯野營地",
      "level": 32,
      "type": "四人迷宮",
      "expansion": "2.x",
      "image": null,
      "tombstoneReward": "詩學古典神典石: 40",
      "specialDrops": ["管弦樂琴樂譜：莫要在野營地撒野"],
      "mechanics": "在開闊的野外環境戰鬥，注意大範圍的攻擊。",
      "description": "曾經的度假勝地，現在被各種野生生物佔領。"
    },
    {
      "id": 8,
      "name": "古代遺跡喀恩埋沒聖堂",
      "level": 35,
      "type": "四人迷宮",
      "expansion": "2.x",
      "image": null,
      "tombstoneReward": "詩學古典神典石: 45",
      "specialDrops": ["管弦樂琴樂譜：昔日的回響", "貝拉哈迪亞玻璃"],
      "mechanics": "探索古代文明的遺跡，解開古老的謎題。",
      "description": "埋藏在地下的古代聖堂，蘊含著失落文明的秘密。"
    },
    {
      "id": 9,
      "name": "流沙迷宮樵鳴洞",
      "level": 38,
      "type": "四人迷宮",
      "expansion": "2.x",
      "image": null,
      "tombstoneReward": "詩學古典神典石: 50",
      "specialDrops": ["九宮幻卡：奇美拉", "管弦樂琴樂譜：憎惡"],
      "mechanics": "在沙漠洞穴中前進，小心流沙和毒氣陷阱。",
      "description": "位於沙漠深處的危險洞穴，充滿致命的陷阱。"
    },
    {
      "id": 10,
      "name": "對龍城塞石衛塔",
      "level": 41,
      "type": "四人迷宮",
      "expansion": "2.x",
      "image": null,
      "tombstoneReward": "詩學古典神典石: 55",
      "specialDrops": ["九宮幻卡：藍龍", "管弦樂琴樂譜：極寒戰線", "戰神鋼"],
      "mechanics": "攀登高塔對抗巨龍，注意龍息和墜落攻擊。",
      "description": "為了對抗巨龍而建造的要塞，見證著龍族戰爭的歷史。"
    },
    {
      "id": 11,
      "name": "山中戰線澤梅爾要塞",
      "level": 44,
      "type": "四人迷宮",
      "expansion": "2.x",
      "image": null,
      "tombstoneReward": "詩學古典神典石: 60",
      "specialDrops": ["九宮幻卡：冥鬼之眼", "管弦樂琴樂譜：澤梅爾要塞"],
      "mechanics": "突破要塞的重重防線，對抗帝國軍的反擊。",
      "description": "加雷馬帝國的軍事要塞，戰略位置極為重要。"
    },
    {
      "id": 12,
      "name": "毒霧洞窟黃金谷",
      "level": 47,
      "type": "四人迷宮",
      "expansion": "2.x",
      "image": null,
      "tombstoneReward": "詩學古典神典石: 65",
      "specialDrops": ["魔界花骨朵", "九宮幻卡：魔界花", "管弦樂琴樂譜：守財奴的愚行", "食蟲植物幼苗"],
      "mechanics": "在充滿毒氣的環境中戰鬥，小心植物怪物的毒性攻擊。",
      "description": "被毒霧籠罩的危險峽谷，生長著各種有毒的植物。"
    },
    {
      "id": 13,
      "name": "神靈聖域放浪神古神殿",
      "level": 50,
      "type": "四人迷宮",
      "expansion": "2.x",
      "image": null,
      "tombstoneReward": "詩學古典神典石: 100",
      "specialDrops": ["一口小果凍", "九宮幻卡：冬貝利", "管弦樂琴樂譜：冬貝利之淚", "尼姆光球"],
      "mechanics": "在神秘的水中神殿探險，對抗古老的海洋生物。",
      "description": "沉沒在海底的古代神殿，供奉著海洋之神。"
    },
    {
      "id": 14,
      "name": "神兵要塞帝國南方堡",
      "level": 50,
      "type": "四人迷宮",
      "expansion": "2.x",
      "image": null,
      "tombstoneReward": "詩學古典神典石: 100",
      "specialDrops": ["九宮幻卡：莉維亞·薩斯·尤尼烏斯"],
      "mechanics": "突破帝國要塞，對抗先進的魔導兵器。",
      "description": "加雷馬帝國的重要軍事基地，配備了最新的魔導科技。"
    },
    {
      "id": 15,
      "name": "最終決戰天幕魔導城",
      "level": 50,
      "type": "四人迷宮",
      "expansion": "2.x",
      "image": null,
      "tombstoneReward": "詩學古典神典石: 150",
      "specialDrops": ["九宮幻卡：蓋烏斯·范·巴埃薩"],
      "mechanics": "在巨大的空中要塞內戰鬥，面對最終BOSS的挑戰。",
      "description": "帝國的終極兵器，飛翔在天空中的巨大要塞。"
    },
    {
      "id": 16,
      "name": "伊弗利特討伐戰",
      "level": 20,
      "type": "8人討伐殲滅戰",
      "expansion": "2.x",
      "image": null,
      "tombstoneReward": "詩學古典神典石: 50",
      "specialDrops": ["伊弗利特之角"],
      "mechanics": "躲避地面火焰，注意地獄烈焰的詠唱。",
      "description": "挑戰火焰蠻神伊弗利特，體驗烈火的洗禮。"
    },
    {
      "id": 17,
      "name": "泰坦討伐戰",
      "level": 34,
      "type": "8人討伐殲滅戰",
      "expansion": "2.x",
      "image": null,
      "tombstoneReward": "詩學古典神典石: 65",
      "specialDrops": ["泰坦之岩"],
      "mechanics": "注意腳下的裂縫，避免被震落平台。",
      "description": "面對大地蠻神泰坦，在搖晃的大地上進行戰鬥。"
    },
    {
      "id": 18,
      "name": "迦樓羅討伐戰",
      "level": 44,
      "type": "8人討伐殲滅戰",
      "expansion": "2.x",
      "image": null,
      "tombstoneReward": "詩學古典神典石: 80",
      "specialDrops": ["迦樓羅之羽"],
      "mechanics": "利用風柱躲避攻擊，注意龍捲風的位置。",
      "description": "面對風暴蠻神迦樓羅，在狂風中尋找勝機。"
    },
    {
      "id": 19,
      "name": "水晶塔 古代人迷宮",
      "level": 50,
      "type": "24人大型任務",
      "expansion": "2.x",
      "image": null,
      "tombstoneReward": "詩學古典神典石: 100",
      "specialDrops": ["九宮幻卡：提坦", "陳舊的樂譜：傲慢", "次元刀的碎片", "亞拉戈魔觸媒"],
      "mechanics": "三個聯盟協調作戰，注意分配攻擊目標。",
      "description": "古代阿拉格帝國的遺跡，需要24名冒險者合作探索。"
    },
    {
      "id": 20,
      "name": "水晶塔 希爾科斯塔",
      "level": 50,
      "type": "24人大型任務",
      "expansion": "2.x",
      "image": null,
      "tombstoneReward": "詩學古典神典石: 100",
      "specialDrops": ["洋蔥小騎士", "九宮幻卡：贊德", "管弦樂琴樂譜：破碎", "寶座水晶塊"],
      "mechanics": "在複雜的塔樓結構中前進，對抗古代的守護者。",
      "description": "水晶塔的中層區域，充滿了古代科技的神秘力量。"
    },
    {
      "id": 21,
      "name": "冰雪廢堡暮衛塔",
      "level": 51,
      "type": "四人迷宮",
      "expansion": "3.x",
      "image": null,
      "tombstoneReward": "詩學古典神典石: 110",
      "specialDrops": ["九宮幻卡：獅鷲", "管弦樂琴樂譜：墮落"],
      "mechanics": "在冰雪環境中戰鬥，注意滑倒和凍結效果。",
      "description": "被冰雪封鎖的古老要塞，寒風呼嘯中隱藏著危險。"
    },
    {
      "id": 22,
      "name": "天山絕頂索姆阿爾靈峰",
      "level": 53,
      "type": "四人迷宮",
      "expansion": "3.x",
      "image": null,
      "tombstoneReward": "詩學古典神典石: 120",
      "specialDrops": ["風箏小貓", "九宮幻卡：刁曼", "管弦樂琴樂譜：永眠"],
      "mechanics": "攀登險峻的山峰，對抗高原上的猛獸。",
      "description": "伊修加德附近的高山，充滿了野生動物和自然陷阱。"
    },
    {
      "id": 23,
      "name": "邪龍王座龍巢神殿",
      "level": 55,
      "type": "四人迷宮",
      "expansion": "3.x",
      "image": null,
      "tombstoneReward": "詩學古典神典石: 130",
      "specialDrops": ["小熊貓", "九宮幻卡：尼德霍格", "管弦樂琴樂譜：邪龍咆哮"],
      "mechanics": "深入邪龍的巢穴，對抗龍族的強大力量。",
      "description": "邪龍尼德霍格的居所，充滿了龍族的威嚴與憤怒。"
    },
    {
      "id": 24,
      "name": "血戰蒼穹魔科學研究所",
      "level": 60,
      "type": "四人迷宮",
      "expansion": "3.x",
      "image": null,
      "tombstoneReward": "詩學古典神典石: 150",
      "specialDrops": ["陳舊的樂譜：異想天開"],
      "mechanics": "躲避激光陷阱，注意機械怪物的自爆攻擊。",
      "description": "伊修加德的秘密研究設施，充滿了先進的魔科學技術。"
    },
    {
      "id": 25,
      "name": "紅玉海底宮殿紫水宮",
      "level": 63,
      "type": "四人迷宮",
      "expansion": "4.x",
      "image": null,
      "tombstoneReward": "詩學古典神典石: 160",
      "specialDrops": ["刺球球", "管弦樂琴樂譜：打開的玉手箱"],
      "mechanics": "水下戰鬥機制，注意氧氣條和水流方向。",
      "description": "沉沒在紅玉海底的古代宮殿，蘊含著東方的神秘力量。"
    },
    {
      "id": 26,
      "name": "解放決戰多瑪王城",
      "level": 67,
      "type": "四人迷宮",
      "expansion": "4.x",
      "image": null,
      "tombstoneReward": "詩學古典神典石: 180",
      "specialDrops": ["迷你格林瓦特", "九宮幻卡：格林瓦特", "管弦樂琴樂譜：月亮門"],
      "mechanics": "在東方城堡中戰鬥，體驗多瑪的解放戰役。",
      "description": "多瑪王國的首都，見證了解放戰爭的關鍵戰役。"
    },
    {
      "id": 27,
      "name": "鏖戰紅蓮阿拉米格",
      "level": 70,
      "type": "四人迷宮",
      "expansion": "4.x",
      "image": null,
      "tombstoneReward": "詩學古典神典石: 200",
      "specialDrops": ["魔導獵手認證密鑰", "九宮幻卡：芝諾斯·耶·加爾烏斯", "管弦樂琴樂譜：自由或是死亡"],
      "mechanics": "最終決戰場，面對帝國的最後抵抗。",
      "description": "阿拉米格解放戰爭的最終戰場，決定命運的關鍵之戰。"
    },
    {
      "id": 28,
      "name": "異界深淵月面地下溪谷",
      "level": 90,
      "type": "四人迷宮",
      "expansion": "6.x",
      "image": null,
      "tombstoneReward": "詩學古典神典石: 100",
      "specialDrops": ["迷你高貝扎", "九宮幻卡：杜蘭特", "管弦樂琴樂譜：巴隆王國 ～曉月～"],
      "mechanics": "在月球地下探索，對抗外星生物的威脅。",
      "description": "月球內部的神秘溪谷，隱藏著古代文明的秘密。"
    },
    {
      "id": 29,
      "name": "忆中金曦亞歷山德里亞",
      "level": 100,
      "type": "四人迷宮",
      "expansion": "7.x",
      "image": null,
      "tombstoneReward": "因果神典石: 50 詩學古典神典石: 20",
      "specialDrops": ["鐵皮哨兵T1", "管弦樂琴樂譜：無盡的旅路"],
      "mechanics": "在回憶中的都市戰鬥，體驗過去的輝煌與悲傷。",
      "description": "記憶中的黃金都市，承載著無數的歷史與情感。"
    },
    {
      "id": 30,
      "name": "荒野秘境仙人刺谷",
      "level": 100,
      "type": "四人迷宮",
      "expansion": "7.x",
      "image": null,
      "tombstoneReward": "因果神典石: 50 詩學古典神典石: 20",
      "specialDrops": ["酒杯刺", "管弦樂琴樂譜：紅土大地的恩惠", "圖拉爾的小蛇的罐子？"],
      "mechanics": "在沙漠中的綠洲戰鬥，小心仙人掌怪物的尖刺攻擊。",
      "description": "新大陸的神秘峽谷，生長著各種奇特的植物。"
    },
    {
      "id": 31,
      "name": "伊弗利特殲滅戰",
      "level": 50,
      "type": "誅滅戰",
      "expansion": "2.x",
      "image": null,
      "tombstoneReward": "詩學古典神典石: 120",
      "specialDrops": ["九宮幻卡：伊弗利特", "伊弗利特之角", "夢魘笛"],
      "mechanics": "極難版本，攻擊力大幅提升，機制更加複雜。",
      "description": "伊弗利特的極難挑戰，獲得專屬坐騎的機會。"
    },
    {
      "id": 32,
      "name": "迦樓羅殲滅戰",
      "level": 50,
      "type": "誅滅戰",
      "expansion": "2.x",
      "image": null,
      "tombstoneReward": "詩學古典神典石: 120",
      "specialDrops": ["九宮幻卡：迦樓羅", "迦樓羅之羽", "夢魘笛"],
      "mechanics": "在狂風中戰鬥，注意風暴的變化和龍捲風攻擊。",
      "description": "迦樓羅的終極考驗，需要完美的走位和時機把握。"
    },
    {
      "id": 33,
      "name": "泰坦殲滅戰",
      "level": 50,
      "type": "誅滅戰",
      "expansion": "2.x",
      "image": null,
      "tombstoneReward": "詩學古典神典石: 120",
      "specialDrops": ["九宮幻卡：泰坦", "泰坦之岩", "夢魘笛"],
      "mechanics": "在不斷縮小的平台上戰鬥，一步錯誤就會墜落。",
      "description": "泰坦的最高難度挑戰，考驗團隊的配合與個人技巧。"
    },
    {
      "id": 34,
      "name": "絕巴哈姆特討伐戰",
      "level": 70,
      "type": "絕境戰",
      "expansion": "4.x",
      "image": null,
      "tombstoneReward": "無",
      "specialDrops": ["龍神圖騰"],
      "mechanics": "極高難度挑戰，需要完美的團隊配合和走位。",
      "description": "最終極的挑戰，只有最強的冒險者才能征服。"
    },
    {
      "id": 35,
      "name": "絕究極神兵討伐戰",
      "level": 70,
      "type": "絕境戰",
      "expansion": "4.x",
      "image": null,
      "tombstoneReward": "無",
      "specialDrops": ["究極圖騰"],
      "mechanics": "面對帝國的終極兵器，需要精確的技能使用。",
      "description": "究極神兵的最高難度版本，終極的機械戰爭。"
    },
    {
      "id": 36,
      "name": "絕亞歷山大討伐戰",
      "level": 80,
      "type": "絕境戰",
      "expansion": "5.x",
      "image": null,
      "tombstoneReward": "無",
      "specialDrops": ["機神城圖騰"],
      "mechanics": "時間操控機制，需要精確的時機控制。",
      "description": "挑戰時間之神亞歷山大，體驗完美的機械美學。"
    },
    {
      "id": 37,
      "name": "邪教駐地無限城古堡",
      "level": 50,
      "type": "四人迷宮",
      "expansion": "2.x",
      "image": null,
      "tombstoneReward": "詩學古典神典石: 20",
      "specialDrops": ["惡魔磚塊", "九宮幻卡：惡魔牆", "管弦樂琴樂譜：古城牆內", "無限城石材"],
      "mechanics": "對抗邪教徒和惡魔，注意黑暗魔法攻擊。",
      "description": "被邪教徒佔領的古老城堡，充滿了黑暗的力量。"
    },
    {
      "id": 38,
      "name": "領航明燈天狼星燈塔",
      "level": 50,
      "type": "四人迷宮",
      "expansion": "2.x",
      "image": null,
      "tombstoneReward": "詩學古典神典石: 30",
      "specialDrops": ["九宮幻卡：塞壬", "陳舊的樂譜：風暴中的燈火"],
      "mechanics": "攀登燈塔對抗海怪，注意水流和風暴效果。",
      "description": "引導船隻的古老燈塔，現在被海怪所佔據。"
    },
    {
      "id": 39,
      "name": "騷亂坑道銅鈴銅山",
      "level": 50,
      "type": "四人迷宮",
      "expansion": "2.x",
      "image": null,
      "tombstoneReward": "詩學古典神典石: 30",
      "specialDrops": ["黏液膠", "陳舊的樂譜：黑暗的擁抱"],
      "mechanics": "在混亂的礦場中戰鬥，小心爆炸和塌陷。",
      "description": "礦場發生暴動後的危險區域，充滿了不穩定因素。"
    },
    {
      "id": 40,
      "name": "惡靈府邸靜語莊園",
      "level": 50,
      "type": "四人迷宮",
      "expansion": "2.x",
      "image": null,
      "tombstoneReward": "詩學古典神典石: 30",
      "specialDrops": ["九宮幻卡：夢魔", "莊園清漆"],
      "mechanics": "對抗更強的惡靈，注意詛咒效果和幻象攻擊。",
      "description": "被更強大邪惡力量侵蝕的莊園，危險程度大幅提升。"
    },
    {
      "id": 41,
      "name": "腐壞遺跡無限城市街古蹟",
      "level": 50,
      "type": "四人迷宮",
      "expansion": "2.x",
      "image": null,
      "tombstoneReward": "詩學古典神典石: 40",
      "specialDrops": ["陳舊的樂譜：魔大戰的傷痕"],
      "mechanics": "探索被腐蝕的古代街道，對抗變異的生物。",
      "description": "古代城市的遺跡，見證了遠古戰爭的痕跡。"
    },
    {
      "id": 42,
      "name": "劍鬥領域日影地修練所",
      "level": 50,
      "type": "四人迷宮",
      "expansion": "2.x",
      "image": null,
      "tombstoneReward": "詩學古典神典石: 40",
      "specialDrops": ["管弦樂琴樂譜：紅蓮戰旗之下"],
      "mechanics": "更激烈的競技場戰鬥，面對更強的對手。",
      "description": "格鬥士的終極試煉場，只有最強者才能生存。"
    },
    {
      "id": 43,
      "name": "紛爭要地布雷福洛克斯野營地",
      "level": 50,
      "type": "四人迷宮",
      "expansion": "2.x",
      "image": null,
      "tombstoneReward": "詩學古典神典石: 40",
      "specialDrops": ["奧猴寶寶", "管弦樂琴樂譜：憤怒"],
      "mechanics": "在戰火紛飛的營地中作戰，注意敵方的戰術配合。",
      "description": "成為戰場的廢棄營地，各方勢力在此爭奪控制權。"
    },
    {
      "id": 44,
      "name": "財寶傳說破艦島",
      "level": 50,
      "type": "四人迷宮",
      "expansion": "2.x",
      "image": null,
      "tombstoneReward": "詩學古典神典石: 50",
      "specialDrops": ["淘氣南加", "管弦樂琴樂譜：越過地平線", "野香蕉的苗"],
      "mechanics": "在海盜島嶼上尋找寶藏，對抗兇猛的海盜和野獸。",
      "description": "傳說中藏有巨大寶藏的神秘島嶼，充滿了危險和機遇。"
    },
    {
      "id": 45,
      "name": "慘劇靈殿塔姆·塔拉墓園",
      "level": 50,
      "type": "四人迷宮",
      "expansion": "2.x",
      "image": null,
      "tombstoneReward": "詩學古典神典石: 50",
      "specialDrops": ["陳舊的樂譜：漆黑的誓言"],
      "mechanics": "面對更強大的亡靈力量，注意黑暗魔法的威脅。",
      "description": "被更深層黑暗力量侵蝕的墓園，死亡的氣息更加濃厚。"
    },
    {
      "id": 46,
      "name": "激戰城塞石衛塔",
      "level": 50,
      "type": "四人迷宮",
      "expansion": "2.x",
      "image": null,
      "tombstoneReward": "詩學古典神典石: 50",
      "specialDrops": ["九宮幻卡：藍龍", "對龍城塞的木材"],
      "mechanics": "更激烈的攻城戰，面對龍族的全力反擊。",
      "description": "龍族戰爭的關鍵戰場，決定戰爭走向的重要據點。"
    },
    {
      "id": 47,
      "name": "凜冽洞天披雪大冰壁",
      "level": 50,
      "type": "四人迷宮",
      "expansion": "2.x",
      "image": null,
      "tombstoneReward": "詩學古典神典石: 70",
      "specialDrops": ["九宮幻卡：芬里爾", "管弦樂琴樂譜：密道"],
      "mechanics": "在極寒環境中戰鬥，對抗冰雪巨狼和寒冰魔法。",
      "description": "被永恆冰雪覆蓋的神秘洞穴，傳說中巨狼的棲息地。"
    },
    {
      "id": 48,
      "name": "逆轉要害薩斯塔夏溶洞",
      "level": 50,
      "type": "四人迷宮",
      "expansion": "2.x",
      "image": null,
      "tombstoneReward": "詩學古典神典石: 70",
      "specialDrops": ["不說話的蜂鳥", "九宮幻卡：海妖", "陳舊的樂譜：激潮", "破損的寶箱"],
      "mechanics": "溶洞發生巨變，水位上升，對抗海洋怪物。",
      "description": "因為海潮變化而改變面貌的溶洞，隱藏著新的危險。"
    },
    {
      "id": 49,
      "name": "甦醒遺跡喀恩埋沒聖堂",
      "level": 50,
      "type": "四人迷宮",
      "expansion": "2.x",
      "image": null,
      "tombstoneReward": "詩學古典神典石: 70",
      "specialDrops": ["小木乃伊", "九宮幻卡：審理神代言者", "管弦樂琴樂譜：落日遺跡"],
      "mechanics": "古代力量甦醒，對抗被喚醒的古代守護者。",
      "description": "古代文明的力量重新甦醒，帶來了新的挑戰和機遇。"
    },
    {
      "id": 50,
      "name": "幻龍殘骸密約之塔",
      "level": 50,
      "type": "四人迷宮",
      "expansion": "2.x",
      "image": null,
      "tombstoneReward": "詩學古典神典石: 100",
      "specialDrops": ["管弦樂琴樂譜：銀淚"],
      "mechanics": "在巨龍遺骸中探索，對抗龍族的怨靈。",
      "description": "古代巨龍的遺骸化成的神秘高塔，蘊含著龍族的力量。"
    },
    {
      "id": 51,
      "name": "武裝聖域放浪神古神殿",
      "level": 50,
      "type": "四人迷宮",
      "expansion": "2.x",
      "image": null,
      "tombstoneReward": "詩學古典神典石: 100",
      "specialDrops": ["九宮幻卡：冬貝利", "九宮幻卡：光鱗兄弟莫拉加加", "管弦樂琴樂譜：聖域陷阱"],
      "mechanics": "神殿被武裝化，對抗更強大的海洋守護者。",
      "description": "經過強化的海底神殿，防禦力和攻擊力都大幅提升。"
    },
    {
      "id": 52,
      "name": "邪念妖地無限城古堡",
      "level": 50,
      "type": "四人迷宮",
      "expansion": "2.x",
      "image": null,
      "tombstoneReward": "詩學古典神典石: 100",
      "specialDrops": ["九宮幻卡：惡魔牆", "九宮幻卡：弗迪亞", "管弦樂琴樂譜：戰禍"],
      "mechanics": "邪念力量達到頂峰，對抗極度強化的惡魔。",
      "description": "被邪惡意念完全侵蝕的古堡，散發著濃厚的惡意。"
    },
    {
      "id": 53,
      "name": "聖教中樞伊修加德教皇廳",
      "level": 57,
      "type": "四人迷宮",
      "expansion": "3.x",
      "image": null,
      "tombstoneReward": "詩學古典神典石: 140",
      "specialDrops": ["獨角幼獸", "九宮幻卡：沙里貝爾", "管弦樂琴樂譜：聖座", "管弦樂琴樂譜：鐘聲", "管弦樂琴樂譜：聖痕"],
      "mechanics": "在神聖的教堂中戰鬥，對抗腐敗的聖職者。",
      "description": "伊修加德的宗教中心，見證了信仰與腐敗的鬥爭。"
    },
    {
      "id": 54,
      "name": "學識寶庫迦巴勒幻想圖書館",
      "level": 59,
      "type": "四人迷宮",
      "expansion": "3.x",
      "image": null,
      "tombstoneReward": "詩學古典神典石: 140",
      "specialDrops": ["63頁", "九宮幻卡：比布魯斯", "管弦樂琴樂譜：萬世箴言"],
      "mechanics": "在魔法圖書館中探索，對抗知識的守護者。",
      "description": "蘊含無盡知識的神奇圖書館，書籍本身就是強大的武器。"
    },
    {
      "id": 55,
      "name": "空中神域不獲島",
      "level": 60,
      "type": "四人迷宮",
      "expansion": "3.x",
      "image": null,
      "tombstoneReward": "詩學古典神典石: 20",
      "specialDrops": ["醜小鴨", "九宮幻卡：招雷巨蛇", "管弦樂琴樂譜：猶如夏雨"],
      "mechanics": "在浮空島嶼上戰鬥，注意雷電和風暴攻擊。",
      "description": "漂浮在空中的神秘島嶼，充滿了天空的力量。"
    },
    {
      "id": 56,
      "name": "博物戰艦無限迴廊",
      "level": 60,
      "type": "四人迷宮",
      "expansion": "3.x",
      "image": null,
      "tombstoneReward": "詩學古典神典石: 20",
      "specialDrops": ["貓頭小鷹", "九宮幻卡：博物總管", "管弦樂琴樂譜：堅不可摧"],
      "mechanics": "在巨大戰艦中探索，對抗機械守衛和展品。",
      "description": "收藏各種珍奇展品的飛空戰艦，每個展品都有其故事。"
    },
    {
      "id": 57,
      "name": "草木庭園聖茉夏娜植物園",
      "level": 60,
      "type": "四人迷宮",
      "expansion": "3.x",
      "image": null,
      "tombstoneReward": "詩學古典神典石: 30",
      "specialDrops": ["葉小妖妖", "九宮幻卡：劇毒美人", "管弦樂琴樂譜：有毒植物"],
      "mechanics": "在植物園中與變異植物戰鬥，小心毒素攻擊。",
      "description": "被魔法影響的植物園，植物們獲得了自主意識。"
    },
    {
      "id": 58,
      "name": "地脈靈燈天狼星燈塔",
      "level": 60,
      "type": "四人迷宮",
      "expansion": "3.x",
      "image": null,
      "tombstoneReward": "詩學古典神典石: 30",
      "specialDrops": ["九宮幻卡：爆彈之母", "管弦樂琴樂譜：觸礁"],
      "mechanics": "燈塔的地脈能量失控，對抗能量體和元素生物。",
      "description": "連接地脈能量的特殊燈塔，能量波動造成了危險。"
    },
    {
      "id": 59,
      "name": "星海空間顛倒塔",
      "level": 60,
      "type": "四人迷宮",
      "expansion": "3.x",
      "image": null,
      "tombstoneReward": "詩學古典神典石: 40",
      "specialDrops": ["卡爾克 布莉娜", "九宮幻卡：卡爾克布莉娜", "管弦樂琴樂譜：跳舞娃娃卡爾克布莉娜 ～蒼穹～", "陳舊的樂譜：上下易位"],
      "mechanics": "在重力顛倒的塔中戰鬥，注意空間的變化。",
      "description": "受到星海力量影響的神奇高塔，重力和空間都被扭曲。"
    },
    {
      "id": 60,
      "name": "神聖遺跡無限城市街古蹟",
      "level": 60,
      "type": "四人迷宮",
      "expansion": "3.x",
      "image": null,
      "tombstoneReward": "詩學古典神典石: 40",
      "specialDrops": ["藍閃蝶", "九宮幻卡：基路伯", "管弦樂琴樂譜：古都"],
      "mechanics": "探索被淨化的古代遺跡，對抗聖光生物。",
      "description": "受到神聖力量洗禮的古代城市，展現出不同的面貌。"
    },
    {
      "id": 61,
      "name": "天龍宮殿憶罪宮",
      "level": 60,
      "type": "四人迷宮",
      "expansion": "3.x",
      "image": null,
      "tombstoneReward": "詩學古典神典石: 50",
      "specialDrops": ["九宮幻卡：赫拉斯瓦爾格", "管弦樂琴樂譜：謝罪之詩"],
      "mechanics": "在龍族的聖地中戰鬥，面對龍王的審判。",
      "description": "龍族的神聖宮殿，記錄著千年戰爭的罪與罰。"
    },
    {
      "id": 62,
      "name": "黑渦傳說破艦島",
      "level": 60,
      "type": "四人迷宮",
      "expansion": "3.x",
      "image": null,
      "tombstoneReward": "詩學古典神典石: 50",
      "specialDrops": ["觸手", "九宮幻卡：大海盜霧鬚王", "管弦樂琴樂譜：神聖的教導"],
      "mechanics": "海盜島被黑暗力量侵蝕，對抗深海怪物。",
      "description": "被深海黑暗力量吞噬的海盜島，危險程度大幅提升。"
    },
    {
      "id": 63,
      "name": "險峻峽谷塞爾法特爾溪谷",
      "level": 60,
      "type": "四人迷宮",
      "expansion": "3.x",
      "image": null,
      "tombstoneReward": "詩學古典神典石: 70",
      "specialDrops": ["疣豬小子", "九宮幻卡：晴天霹靂托佐爾·法托特爾"],
      "mechanics": "在崎嶇的峽谷中作戰，小心落石和地形陷阱。",
      "description": "地形險峻的深山峽谷，隱藏著古老的秘密。"
    },
    {
      "id": 64,
      "name": "秘本寶庫迦巴勒幻想圖書館",
      "level": 60,
      "type": "四人迷宮",
      "expansion": "3.x",
      "image": null,
      "tombstoneReward": "詩學古典神典石: 70",
      "specialDrops": ["九宮幻卡：博學林鴞", "管弦樂琴樂譜：恐書症", "真妖異全集手抄本"],
      "mechanics": "圖書館的深層區域，對抗更強大的知識守護者。",
      "description": "圖書館的秘密區域，收藏著禁忌的知識和力量。"
    },
    {
      "id": 65,
      "name": "堅牢鐵壁巴埃薩長城",
      "level": 60,
      "type": "四人迷宮",
      "expansion": "3.x",
      "image": null,
      "tombstoneReward": "詩學古典神典石: 100",
      "specialDrops": ["鬥牛小犬", "九宮幻卡：鐵面公卿"],
      "mechanics": "突破帝國的防禦要塞，對抗重裝部隊。",
      "description": "加雷馬帝國的防禦長城，象徵著帝國的軍事力量。"
    },
    {
      "id": 66,
      "name": "天山深境索姆阿爾靈峰",
      "level": 60,
      "type": "四人迷宮",
      "expansion": "3.x",
      "image": null,
      "tombstoneReward": "詩學古典神典石: 100",
      "specialDrops": ["九宮幻卡：熔岩蠍"],
      "mechanics": "深入山峰內部，對抗火山中的岩漿生物。",
      "description": "高山深處的秘密通道，連接著地底的熔岩世界。"
    },
    {
      "id": 67,
      "name": "漂流海域妖歌海",
      "level": 61,
      "type": "四人迷宮",
      "expansion": "4.x",
      "image": null,
      "tombstoneReward": "詩學古典神典石: 160",
      "specialDrops": ["吉多", "管弦樂琴樂譜：通向黎明"],
      "mechanics": "在海上與人魚和海怪戰鬥，注意海浪的影響。",
      "description": "被人魚歌聲籠罩的神秘海域，美麗而危險。"
    },
    {
      "id": 68,
      "name": "試煉行路巴兒達木霸道",
      "level": 65,
      "type": "四人迷宮",
      "expansion": "4.x",
      "image": null,
      "tombstoneReward": "詩學古典神典石: 170",
      "specialDrops": ["旅雀兒", "管弦樂琴樂譜：英雄未成"],
      "mechanics": "在東方的山路上前進，對抗盜賊和野獸。",
      "description": "通往東方的重要道路，考驗著旅人的決心和勇氣。"
    },
    {
      "id": 69,
      "name": "巨砲要塞帝國白山堡",
      "level": 69,
      "type": "四人迷宮",
      "expansion": "4.x",
      "image": null,
      "tombstoneReward": "詩學古典神典石: 190",
      "specialDrops": ["魔導復仇者追蹤型", "管弦樂琴樂譜：異形"],
      "mechanics": "攻破帝國的巨砲要塞，對抗先進的魔導兵器。",
      "description": "配備巨型火砲的帝國要塞，火力強大難以接近。"
    },
    {
      "id": 70,
      "name": "惡黨孤城黃金閣",
      "level": 70,
      "type": "四人迷宮",
      "expansion": "4.x",
      "image": null,
      "tombstoneReward": "詩學古典神典石: 20",
      "specialDrops": ["新型迷你夕霧", "管弦樂琴樂譜：策謀", "破碎的般若面具"],
      "mechanics": "在東方的豪華建築中與忍者和武士戰鬥。",
      "description": "被惡徒佔領的金碧輝煌宮殿，隱藏著政治陰謀。"
    },
    {
      "id": 71,
      "name": "修行古剎星導寺",
      "level": 70,
      "type": "四人迷宮",
      "expansion": "4.x",
      "image": null,
      "tombstoneReward": "詩學古典神典石: 20",
      "specialDrops": ["伊沃恩玩偶", "管弦樂琴樂譜：豹頭環眼"],
      "mechanics": "在古老的寺廟中修行戰鬥，對抗妖魔鬼怪。",
      "description": "東方的神聖寺廟，僧侶們在此修行和除魔。"
    },
    {
      "id": 72,
      "name": "沉沒神殿斯卡拉遺跡",
      "level": 70,
      "type": "四人迷宮",
      "expansion": "4.x",
      "image": null,
      "tombstoneReward": "詩學古典神典石: 30",
      "specialDrops": ["椒鹽海豹", "九宮幻卡：直言不諱赫羅德里克", "管弦樂琴樂譜：離鄉"],
      "mechanics": "在水下遺跡中探索，對抗古代的海洋生物。",
      "description": "沉沒在海底的古代神殿，見證著失落文明的輝煌。"
    },
    {
      "id": 73,
      "name": "紅玉火山獄之蓋",
      "level": 70,
      "type": "四人迷宮",
      "expansion": "4.x",
      "image": null,
      "tombstoneReward": "詩學古典神典石: 40",
      "specialDrops": ["白鼬", "九宮幻卡：玄武", "管弦樂琴樂譜：鬼島"],
      "mechanics": "在活火山內部戰鬥，對抗火元素和岩漿生物。",
      "description": "封印在火山中的古代監獄，炙熱的環境充滿危險。"
    },
    {
      "id": 74,
      "name": "瘋狂戰艦無限迴廊",
      "level": 70,
      "type": "四人迷宮",
      "expansion": "4.x",
      "image": null,
      "tombstoneReward": "詩學古典神典石: 40",
      "specialDrops": ["九宮幻卡：導航系統", "管弦樂琴樂譜：堅不可摧（身心二元）"],
      "mechanics": "戰艦系統失控，在混亂的環境中對抗機械怪物。",
      "description": "戰艦的控制系統發生故障，整艘船陷入混亂狀態。"
    },
    {
      "id": 75,
      "name": "風水靈廟岩燕廟",
      "level": 70,
      "type": "四人迷宮",
      "expansion": "4.x",
      "image": null,
      "tombstoneReward": "詩學古典神典石: 50",
      "specialDrops": ["齊天小聖", "九宮幻卡：齊天大聖", "管弦樂琴樂譜：風水寶地"],
      "mechanics": "在東方風水寶地中戰鬥，對抗神猴和天兵。",
      "description": "供奉齊天大聖的神聖廟宇，充滿了東方神話的力量。"
    },
    {
      "id": 76,
      "name": "死亡大地終末焦土",
      "level": 70,
      "type": "四人迷宮",
      "expansion": "4.x",
      "image": null,
      "tombstoneReward": "詩學古典神典石: 70",
      "specialDrops": ["九宮幻卡：霧龍", "管弦樂琴樂譜：死亡大地"],
      "mechanics": "在被詛咒的焦土上戰鬥，對抗死亡的力量。",
      "description": "被死亡詛咒籠罩的荒涼大地，生命在此無法存在。"
    },
    {
      "id": 77,
      "name": "污染庭園聖茉夏娜植物園",
      "level": 70,
      "type": "四人迷宮",
      "expansion": "4.x",
      "image": null,
      "tombstoneReward": "詩學古典神典石: 70",
      "specialDrops": ["泥小點", "九宮幻卡：枯腐泥妖", "管弦樂琴樂譜：泥中蓮花", "翠綠隔離牆"],
      "mechanics": "植物園受到污染，對抗變異的有毒植物。",
      "description": "被有毒物質污染的植物園，生態系統完全失衡。"
    },
    {
      "id": 78,
      "name": "國境防線基姆利特暗區",
      "level": 70,
      "type": "四人迷宮",
      "expansion": "4.x",
      "image": null,
      "tombstoneReward": "詩學古典神典石: 100",
      "specialDrops": ["迷你武裝重甲", "九宮幻卡：普羅米修斯", "管弦樂琴樂譜：硝煙瀰漫"],
      "mechanics": "在國境防線上戰鬥，對抗敵國的入侵部隊。",
      "description": "保衛國家邊境的重要防線，戰火不斷的前線戰場。"
    },
    {
      "id": 79,
      "name": "遇襲集落水灘村",
      "level": 71,
      "type": "四人迷宮",
      "expansion": "5.x",
      "image": null,
      "tombstoneReward": "詩學古典神典石: 110",
      "specialDrops": ["黑豆柴", "九宮幻卡：斐利亞", "管弦樂琴樂譜：烈火與利劍"],
      "mechanics": "保衛遭受攻擊的村莊，對抗入侵的敵人。",
      "description": "受到襲擊的和平村莊，村民們需要冒險者的保護。"
    },
    {
      "id": 80,
      "name": "水妖幻園多恩美格禁園",
      "level": 73,
      "type": "四人迷宮",
      "expansion": "5.x",
      "image": null,
      "tombstoneReward": "詩學古典神典石: 120",
      "specialDrops": ["石蓮小猬", "管弦樂琴樂譜：虛構", "禁園花架"],
      "mechanics": "在夢幻的禁園中戰鬥，對抗水妖和幻象。",
      "description": "被水妖魔法籠罩的禁忌花園，現實與幻想交織。"
    },
    {
      "id": 81,
      "name": "文明古蹟奇坦那神影洞",
      "level": 75,
      "type": "四人迷宮",
      "expansion": "5.x",
      "image": null,
      "tombstoneReward": "詩學古典神典石: 130",
      "specialDrops": ["變色龍", "九宮幻卡：艾洛斯", "管弦樂琴樂譜：解讀", "倒樹"],
      "mechanics": "探索古代文明遺跡，解開古老的謎題。",
      "description": "古代文明留下的神秘洞穴，隱藏著失落的知識。"
    },
    {
      "id": 82,
      "name": "避暑離宮馬利卡大井",
      "level": 77,
      "type": "四人迷宮",
      "expansion": "5.x",
      "image": null,
      "tombstoneReward": "詩學古典神典石: 140",
      "specialDrops": ["小犰狳", "九宮幻卡：斯托爾戈", "管弦樂琴樂譜：幽深", "壁掛鐵架火炬"],
      "mechanics": "在地下深井中探索，對抗地底的古代生物。",
      "description": "貴族的避暑別墅下的神秘深井，深不見底。"
    },
    {
      "id": 83,
      "name": "偽造天界格魯格火山",
      "level": 79,
      "type": "四人迷宮",
      "expansion": "5.x",
      "image": null,
      "tombstoneReward": "詩學古典神典石: 150",
      "specialDrops": ["得到寬恕的仇恨", "管弦樂琴樂譜：兇獸腹中", "格魯格盆栽"],
      "mechanics": "在人造天界中戰鬥，對抗被操控的天使。",
      "description": "人工創造的虛假天界，扭曲了神聖的概念。"
    },
    {
      "id": 84,
      "name": "末日暗影亞馬烏羅提",
      "level": 80,
      "type": "四人迷宮",
      "expansion": "5.x",
      "image": null,
      "tombstoneReward": "詩學古典神典石: 20",
      "specialDrops": ["鯨頭鸛", "管弦樂琴樂譜：末日時刻"],
      "mechanics": "在末日陰影中戰鬥，見證文明的終結。",
      "description": "被末日陰影籠罩的古代都市，展現著文明的脆弱。"
    },
    {
      "id": 85,
      "name": "異界遺構希爾科斯孿晶塔",
      "level": 80,
      "type": "四人迷宮",
      "expansion": "5.x",
      "image": null,
      "tombstoneReward": "詩學古典神典石: 20",
      "specialDrops": ["管弦樂琴樂譜：一瞬千里"],
      "mechanics": "在雙子水晶塔中戰鬥，體驗空間的扭曲。",
      "description": "由雙子水晶構成的神秘高塔，連接著不同的空間。"
    },
    {
      "id": 86,
      "name": "創造機構阿尼德羅學院",
      "level": 80,
      "type": "四人迷宮",
      "expansion": "5.x",
      "image": null,
      "tombstoneReward": "詩學古典神典石: 20",
      "specialDrops": ["小小冰海天使", "管弦樂琴樂譜：無影之影"],
      "mechanics": "在創造學院中戰鬥，對抗失控的創造物。",
      "description": "研究創造技術的高等學院，實驗體失去控制。"
    },
    {
      "id": 87,
      "name": "魔法宮殿宇宙宮",
      "level": 80,
      "type": "四人迷宮",
      "expansion": "5.x",
      "image": null,
      "tombstoneReward": "詩學古典神典石: 30",
      "specialDrops": ["小涼南希", "九宮幻卡：漆黑導師", "管弦樂琴樂譜：華美宮殿", "宇宙宮隔斷", "宇宙宮掛飾"],
      "mechanics": "在華麗的宇宙宮殿中戰鬥，對抗宇宙的力量。",
      "description": "充滿宇宙奧秘的魔法宮殿，星空在此觸手可及。"
    },
    {
      "id": 88,
      "name": "黑風海底阿尼德羅追憶館",
      "level": 80,
      "type": "四人迷宮",
      "expansion": "5.x",
      "image": null,
      "tombstoneReward": "詩學古典神典石: 40",
      "specialDrops": ["小小古代人", "九宮幻卡：不明物體", "管弦樂琴樂譜：潛伏於沙"],
      "mechanics": "在海底的記憶殿堂中戰鬥，對抗過去的陰影。",
      "description": "保存古代記憶的海底建築，過去的影像在此重現。"
    },
    {
      "id": 89,
      "name": "暗影決戰諾弗蘭特",
      "level": 80,
      "type": "四人迷宮",
      "expansion": "5.x",
      "image": null,
      "tombstoneReward": "詩學古典神典石: 50",
      "specialDrops": ["幻影亡靈法師", "管弦樂琴樂譜：異路同歸"],
      "mechanics": "在光明與黑暗的決戰中戰鬥，決定世界的命運。",
      "description": "光明與黑暗的最終決戰場，世界的平衡在此決定。"
    },
    {
      "id": 90,
      "name": "魔術工房瑪托雅工作室",
      "level": 80,
      "type": "四人迷宮",
      "expansion": "5.x",
      "image": null,
      "tombstoneReward": "詩學古典神典石: 70",
      "specialDrops": ["水小滴", "九宮幻卡：仙子豬之母", "管弦樂琴樂譜：剛出爐的仙子豬"],
      "mechanics": "在魔法工作室中戰鬥，對抗失控的魔法實驗。",
      "description": "著名魔法師的私人工作室，充滿了神奇的魔法道具。"
    },
    {
      "id": 91,
      "name": "黃金平原帕戈爾贊草原",
      "level": 80,
      "type": "四人迷宮",
      "expansion": "5.x",
      "image": null,
      "tombstoneReward": "詩學古典神典石: 100",
      "specialDrops": ["魔導獵手追蹤型", "九宮幻卡：真月巴哈姆特", "管弦樂琴樂譜：烈火七部族"],
      "mechanics": "在廣闊的草原上戰鬥，面對龍神的最終考驗。",
      "description": "傳說中的黃金草原，龍神巴哈姆特的最後棲息地。"
    },
    {
      "id": 92,
      "name": "異形樓閣佐特塔",
      "level": 81,
      "type": "四人迷宮",
      "expansion": "6.x",
      "image": null,
      "tombstoneReward": "詩學古典神典石: 110",
      "specialDrops": ["梅加斯三姐妹之形", "九宮幻卡：梅加斯三姐妹", "管弦樂琴樂譜：佐特塔"],
      "mechanics": "在奇異的高塔中戰鬥，對抗三位神秘姐妹。",
      "description": "造型奇特的神秘高塔，三位姐妹在此守護著秘密。"
    },
    {
      "id": 93,
      "name": "魔導神門巴別塔",
      "level": 83,
      "type": "四人迷宮",
      "expansion": "6.x",
      "image": null,
      "tombstoneReward": "詩學古典神典石: 120",
      "specialDrops": ["阿尼瑪之形", "九宮幻卡：阿尼瑪", "管弦樂琴樂譜：加雷馬快列"],
      "mechanics": "攀登通天的魔導高塔，對抗帝國的終極兵器。",
      "description": "帝國建造的通天巨塔，象徵著科技與野心的結合。"
    },
    {
      "id": 94,
      "name": "末日樹海萬相森國",
      "level": 85,
      "type": "四人迷宮",
      "expansion": "6.x",
      "image": null,
      "tombstoneReward": "詩學古典神典石: 130",
      "specialDrops": ["河馬幼崽", "管弦樂琴樂譜：天空燃燒之日"],
      "mechanics": "在變化萬千的森林中戰鬥，適應不斷變化的環境。",
      "description": "充滿變化的神奇森林，每一刻都呈現不同的面貌。"
    },
    {
      "id": 95,
      "name": "創造環境極北造物院",
      "level": 87,
      "type": "四人迷宮",
      "expansion": "6.x",
      "image": null,
      "tombstoneReward": "詩學古典神典石: 140",
      "specialDrops": ["神杖小蛇", "九宮幻卡：赫爾墨斯", "管弦樂琴樂譜：創造之奇蹟", "極北造物院座椅"],
      "mechanics": "在創造實驗室中戰鬥，對抗被創造的生命體。",
      "description": "研究生命創造的秘密實驗室，充滿了倫理的爭議。"
    },
    {
      "id": 96,
      "name": "星海深幽尋因星晶鏡",
      "level": 89,
      "type": "四人迷宮",
      "expansion": "6.x",
      "image": null,
      "tombstoneReward": "詩學古典神典石: 150",
      "specialDrops": ["小巨魔", "九宮幻卡：邪執外道的亞蒙", "管弦樂琴樂譜：星海", "尋因工作台", "尋因檯燈"],
      "mechanics": "在星海深處探索真相，對抗阻礙者的陰謀。",
      "description": "探索宇宙奧秘的觀測設施，真相就在星海深處。"
    },
    {
      "id": 97,
      "name": "最終幻想末世終跡",
      "level": 90,
      "type": "四人迷宮",
      "expansion": "6.x",
      "image": null,
      "tombstoneReward": "詩學古典神典石: 20",
      "specialDrops": ["遊星鳥", "管弦樂琴樂譜：先逝的群星"],
      "mechanics": "在世界的終點戰鬥，面對最終的審判。",
      "description": "一切終結的地方，見證著世界的最後時刻。"
    },
    {
      "id": 98,
      "name": "樂園都市笑笑鎮",
      "level": 90,
      "type": "四人迷宮",
      "expansion": "6.x",
      "image": null,
      "tombstoneReward": "詩學古典神典石: 20",
      "specialDrops": ["月面仙人刺王子", "管弦樂琴樂譜：開開心心紅蘿蔔"],
      "mechanics": "在詭異的歡樂城市中戰鬥，揭開快樂的假象。",
      "description": "表面歡樂的城市，隱藏著令人不安的真相。"
    },
    {
      "id": 99,
      "name": "電腦夢境斯提格瑪四",
      "level": 90,
      "type": "四人迷宮",
      "expansion": "6.x",
      "image": null,
      "tombstoneReward": "詩學古典神典石: 20",
      "specialDrops": ["集成奧密克戎"],
      "mechanics": "在虛擬世界中戰鬥，對抗數位化的敵人。",
      "description": "由電腦程序構成的虛擬世界，現實與虛擬的界限模糊。"
    },
    {
      "id": 100,
      "name": "近東秘寶阿爾扎達爾海底遺跡群",
      "level": 90,
      "type": "四人迷宮",
      "expansion": "6.x",
      "image": null,
      "tombstoneReward": "詩學古典神典石: 30",
      "specialDrops": ["門小奴", "九宮幻卡：鐵壁", "管弦樂琴樂譜：打開的地圖", "阿爾扎達爾園藝燈"],
      "mechanics": "在海底遺跡中尋找寶藏，對抗古代的守護者。",
      "description": "沉沒在海底的古代城市群，蘊藏著無數的秘密寶藏。"
    },
    {
      "id": 101,
      "name": "異界孤城特羅亞宮廷",
      "level": 90,
      "type": "四人迷宮",
      "expansion": "6.x",
      "image": null,
      "tombstoneReward": "詩學古典神典石: 40",
      "specialDrops": ["斯卡米留尼之形", "九宮幻卡：貝雅特麗齊", "管弦樂琴樂譜：特羅亞國 ～曉月～", "管弦樂琴樂譜：戰鬥2（最終幻想IV） ～曉月～", "首席神官的椅子", "土之大妖異的寶珠"],
      "mechanics": "在異界的孤立宮廷中戰鬥，體驗古典的悲劇。",
      "description": "被隔離在異界的古代宮廷，重現著悲劇的命運。"
    },
    {
      "id": 102,
      "name": "雪山奧窟冥魂石洞",
      "level": 90,
      "type": "四人迷宮",
      "expansion": "6.x",
      "image": null,
      "tombstoneReward": "詩學古典神典石: 50",
      "specialDrops": ["凱納槽之形", "九宮幻卡：凱納槽", "管弦樂琴樂譜：洞中青輝", "冥魂石洞標旗", "水之大妖異的寶珠"],
      "mechanics": "在雪山深處的洞穴中探索，對抗冰雪和靈魂的力量。",
      "description": "隱藏在雪山深處的神秘洞穴，冥魂石散發著詭異的光芒。"
    },
    {
      "id": 103,
      "name": "間歇靈泉哈姆島",
      "level": 90,
      "type": "四人迷宮",
      "expansion": "6.x",
      "image": null,
      "tombstoneReward": "詩學古典神典石: 70",
      "specialDrops": ["海鸚", "九宮幻卡：八足巨妖", "管弦樂琴樂譜：星球的嘆息"],
      "mechanics": "在溫泉島嶼上戰鬥，享受溫泉的治癒效果。",
      "description": "擁有神奇溫泉的小島，溫泉水具有治癒的力量。"
    },
    {
      "id": 104,
      "name": "叢林競流生息河岸",
      "level": 91,
      "type": "四人迷宮",
      "expansion": "6.x",
      "image": null,
      "tombstoneReward": "詩學古典神典石: 110",
      "specialDrops": ["小小海牛", "九宮幻卡：瞌睡怪", "管弦樂琴樂譜：海牛逆流而上", "生息花叢"],
      "mechanics": "在充滿生機的河岸叢林中戰鬥，與自然和諧共處。",
      "description": "生機勃勃的叢林河岸，各種生物在此繁衍生息。"
    },
    {
      "id": 105,
      "name": "通天絕壁沃刻佐莫山",
      "level": 93,
      "type": "四人迷宮",
      "expansion": "6.x",
      "image": null,
      "tombstoneReward": "詩學古典神典石: 120",
      "specialDrops": ["洛洛洛特雪精", "九宮幻卡：遼刻特特雪精", "管弦樂琴樂譜：高聳入雲", "佐莫石燈籠"],
      "mechanics": "攀登直插雲霄的絕壁，對抗高山上的雪精靈。",
      "description": "高聳入雲的險峻山峰，雪精靈們在此守護著山頂的秘密。"
    },
    {
      "id": 106,
      "name": "神聖禁地深空天坑",
      "level": 95,
      "type": "四人迷宮",
      "expansion": "6.x",
      "image": null,
      "tombstoneReward": "詩學古典神典石: 130",
      "specialDrops": ["說話的石頭", "九宮幻卡：鎚顱巨兵", "管弦樂琴樂譜：樹海深處之夢", "天坑室內燈"],
      "mechanics": "深入神聖的天坑，對抗古代的石像巨兵。",
      "description": "被視為神聖禁地的巨大天坑，深不見底的洞穴充滿謎團。"
    },
    {
      "id": 107,
      "name": "前哨基地先鋒營",
      "level": 97,
      "type": "四人迷宮",
      "expansion": "6.x",
      "image": null,
      "tombstoneReward": "詩學古典神典石: 140",
      "specialDrops": ["飛梭M9", "管弦樂琴樂譜：火花與閃光", "雷轉質砲塔"],
      "mechanics": "在前線基地中戰鬥，對抗敵軍的突襲。",
      "description": "建立在前線的軍事基地，隨時面臨敵軍的威脅。"
    },
    {
      "id": 108,
      "name": "魂魄工廠創生設施",
      "level": 99,
      "type": "四人迷宮",
      "expansion": "6.x",
      "image": null,
      "tombstoneReward": "詩學古典神典石: 150",
      "specialDrops": ["驗證體安布羅斯", "九宮幻卡：安布羅斯", "管弦樂琴樂譜：解剖生命", "創生設施螢幕桌", "創生設施辦公椅"],
      "mechanics": "在生命創造工廠中戰鬥，對抗人造生命體。",
      "description": "研究靈魂與生命奧秘的工廠，創造著不自然的存在。"
    },
    {
      "id": 109,
      "name": "噩夢樂園迷途鬼區",
      "level": 100,
      "type": "四人迷宮",
      "expansion": "7.x",
      "image": null,
      "tombstoneReward": "因果神典石: 50 詩學古典神典石: 20",
      "specialDrops": ["惡作劇小丑", "管弦樂琴樂譜：不見月明的小丑 ～金曦～", "迷途鬼區壁燈", "夢像地板貼"],
      "mechanics": "在扭曲的遊樂園中戰鬥，對抗瘋狂的小丑和幻象。",
      "description": "曾經歡樂的遊樂園變成了噩夢，小丑們失去了理智。"
    },
    {
      "id": 110,
      "name": "廢棄據點玉韋亞瓦塔實驗站",
      "level": 100,
      "type": "四人迷宮",
      "expansion": "7.x",
      "image": null,
      "tombstoneReward": "因果神典石: 80 詩學古典神典石: 50",
      "specialDrops": ["躍陽兔", "九宮幻卡：卡尼洛喀站長", "管弦樂琴樂譜：兇猛的容器"],
      "mechanics": "在廢棄的實驗站中探索，對抗失控的實驗體。",
      "description": "被遺棄的科學實驗站，實驗體們在此自由遊蕩。"
    }
  ]
}